[{"key":5,"title":"hello ","content":"hjk","url":"ghji"},{"key":4,"title":"key","content":"data","url":"see"},{"key":3,"title":"hello ","content":"hello ","url":"https://iot-webshop.com/#:~:text=Our%20webshop%20offers,and%20several%20others."},{"key":2,"title":"time ","content":"\"Our webshop offers Gateways supporting LoRaWAN® The gateways will be able to work with all standard LoRaWAN servers like Loriot, TTN/TTI, Chirpstack and many others. In most cases we can also deliver gateways that can connect directly to network providers like Helium, AWS, Netmore, Cibicom and several others.\"\n https://iot-webshop.com/#:~:text=Our%20webshop%20offers,and%20several%20others.","url":"https://iot-webshop.com/#:~:text=Our%20webshop%20offers,and%20several%20others."},{"key":1,"title":"Tutty 👋👋👋🤗","content":"\"Our webshop offers Gateways supporting LoRaWAN® The gateways will be able to work with all standard LoRaWAN servers like Loriot, TTN/TTI, Chirpstack and many others. In most cases we can also deliver gateways that can connect directly to network providers like Helium, AWS, Netmore, Cibicom and several others.\"\n https://iot-webshop.com/#:~:text=Our%20webshop%20offers,and%20several%20others.","url":"https://iot-webshop.com/#:~:text=Our%20webshop%20offers,and%20several%20others."},{"key":0,"title":"hello ","content":"hello ","url":"hello "}]